iterator_chain/__init__.py
iterator_chain/begin.py
iterator_chain/intermediate.py
iterator_chain/parallel_intermediate.py
iterator_chain-1.1.0.dist-info/LICENSE
iterator_chain-1.1.0.dist-info/METADATA
iterator_chain-1.1.0.dist-info/WHEEL
iterator_chain-1.1.0.dist-info/top_level.txt
iterator_chain-1.1.0.dist-info/RECORD
