Metadata-Version: 2.1
Name: iterator-chain
Version: 1.1.0
Summary: Chain together lazily computed modifications to iterators
Home-page: https://github.com/halprin/iterator-chain
Author: halprin
Author-email: me@halprin.io
License: UNKNOWN
Platform: UNKNOWN
Classifier: Programming Language :: Python :: 3
Classifier: License :: OSI Approved :: MIT License
Classifier: Operating System :: OS Independent
Classifier: Topic :: Software Development :: Libraries :: Python Modules
